{
    "name": "Relevanssi - A Better Search",
    "version": "3.5.6.1",
    "url": "https:\/\/wordpress.org\/plugins\/relevanssi",
    "primaryKeys": {
        "relevanssi": {
            "key": [
                "doc",
                "term",
                "item"
            ],
            "auto_increment": false
        },
        "relevanssi_log": {
            "key": [
                "id"
            ]
        }
    },
    "foreignKeys": {
        "relevanssi_log:user_id": "users:ID"
    },
    "ignore": [
        {
            "relevanssi": "(.*)"
        },
        {
            "relevanssi_log": "(.*)"
        },
        {
            "relevanssi_stopwords": "(.*)"
        }
    ]
}